nfselib.ginfes-0.2.0-py3.8-nspkg.pth
nfselib/ginfes/__init__.py
nfselib/ginfes/docs/conf.py
nfselib/ginfes/docs/module_contents.txt
nfselib/ginfes/v3_01/__init__.py
nfselib/ginfes/v3_01/cabecalho.py
nfselib/ginfes/v3_01/generatedsnamespaces.py
nfselib/ginfes/v3_01/servico_cancelar_nfse_envio.py
nfselib/ginfes/v3_01/servico_cancelar_nfse_resposta.py
nfselib/ginfes/v3_01/servico_consultar_lote_rps_envio.py
nfselib/ginfes/v3_01/servico_consultar_lote_rps_resposta.py
nfselib/ginfes/v3_01/servico_consultar_nfse_resposta.py
nfselib/ginfes/v3_01/servico_consultar_nfse_rps_envio.py
nfselib/ginfes/v3_01/servico_consultar_situacao_lote_rps_envio.py
nfselib/ginfes/v3_01/servico_consultar_situacao_lote_rps_resposta.py
nfselib/ginfes/v3_01/servico_enviar_lote_rps_envio.py
nfselib/ginfes/v3_01/servico_enviar_lote_rps_resposta.py
nfselib.ginfes-0.2.0.dist-info/AUTHORS.rst
nfselib.ginfes-0.2.0.dist-info/LICENSE
nfselib.ginfes-0.2.0.dist-info/METADATA
nfselib.ginfes-0.2.0.dist-info/WHEEL
nfselib.ginfes-0.2.0.dist-info/namespace_packages.txt
nfselib.ginfes-0.2.0.dist-info/top_level.txt
nfselib.ginfes-0.2.0.dist-info/RECORD
